paylink_sdk/__init__.py
paylink_sdk/client.py
paylink_sdk/langchain_adapter/__init__.py
paylink_sdk/langchain_adapter/toolkit.py
paylink_sdk/openai_adapter/__init__.py
paylink_sdk/openai_adapter/toolkit.py
paylink_sdk-0.4.0.dist-info/METADATA
paylink_sdk-0.4.0.dist-info/WHEEL
paylink_sdk-0.4.0.dist-info/licenses/LICENSE
paylink_sdk-0.4.0.dist-info/RECORD
