Metadata-Version: 2.4
Name: paylink-sdk
Version: 0.4.0
Summary: Python SDK for interacting with the PayLink MCP Server
Project-URL: Homepage, https://github.com/jameskanyiri/paylink-sdk
Project-URL: Repository, https://github.com/jameskanyiri/paylink-sdk
Project-URL: Issues, https://github.com/jameskanyiri/paylink-sdk/issues
Project-URL: Documentation, https://github.com/jameskanyiri/paylink-sdk#readme
Project-URL: Changelog, https://github.com/jameskanyiri/paylink-sdk#changelog
Author-email: James Kanyiri <jameskanyiridev@gmail.com>
License-File: LICENSE
Keywords: africa,financial integration,fintech,mcp,mobile money,mpesa,payment
Classifier: Development Status :: 4 - Beta
Classifier: Intended Audience :: Developers
Classifier: License :: OSI Approved :: MIT License
Classifier: Operating System :: OS Independent
Classifier: Programming Language :: Python :: 3.13
Classifier: Topic :: Office/Business :: Financial
Classifier: Topic :: Software Development :: Libraries :: Python Modules
Requires-Python: >=3.13
Requires-Dist: mcp>=1.9.2
Provides-Extra: dev
Requires-Dist: build>=1.2.2.post1; extra == 'dev'
Requires-Dist: hatch>=1.14.1; extra == 'dev'
Requires-Dist: ipykernel>=6.29.5; extra == 'dev'
Requires-Dist: pytest-asyncio>=0.26.0; extra == 'dev'
Requires-Dist: pytest>=8.3.5; extra == 'dev'
Requires-Dist: twine>=6.1.0; extra == 'dev'
